{
    "condition": "minecraft:alternative",
    "terms": [
      {
        "condition": "minecraft:entity_properties",
        "entity": "this",
        "predicate": {
          "equipment": {
            "mainhand": {
              "nbt": "{20w14s:{cat_item:1b}}"
            }
          }
        }
      },
      {
        "condition": "minecraft:inverted",
        "term": {
          "condition": "minecraft:alternative",
          "terms": [
            {
              "condition": "minecraft:entity_properties",
              "entity": "this",
              "predicate": {
                "equipment": {
                  "mainhand": {
                    "item": "minecraft:lead"
                  }
                }
              }
            },
            {
              "condition": "minecraft:inverted",
              "term": {
                "condition": "minecraft:entity_properties",
                "entity": "this",
                "predicate": {
                  "equipment": {
                    "offhand": {
                      "nbt": "{20w14s:{cat_item:1b}}"
                    }
                  }
                }
              }
            }
          ]
        }
      }
    ]
  }
