{
  "pools": [
    {
      "rolls": 3,
      "entries": [
        {
          "type": "minecraft:item",
          "name": "minecraft:mossy_cobblestone",
          "weight": 1,
          "functions": [
            {
              "function": "minecraft:set_count",
              "count": {
                "min": 8,
                "max": 16
              }
            }
          ]
        },
        {
          "type": "minecraft:item",
          "name": "minecraft:oak_leaves",
          "weight": 1,
          "functions": [
            {
              "function": "minecraft:set_count",
              "count": {
                "min": 16,
                "max": 32
              }
            }
          ]
        },
        {
          "type": "minecraft:loot_table",
          "name": "minecraft:chests/simple_dungeon",
          "weight": 1
        },
        {
          "type": "minecraft:loot_table",
          "name": "20w14s:treasure",
          "weight": 1
        }
      ]
    }
  ]
}